yookassa/__init__.py
yookassa/client.py
yookassa/configuration.py
yookassa/deal.py
yookassa/domain/__init__.py
yookassa/domain/common/__init__.py
yookassa/domain/common/base_object.py
yookassa/domain/common/confirmation_type.py
yookassa/domain/common/context.py
yookassa/domain/common/data_context.py
yookassa/domain/common/http_verb.py
yookassa/domain/common/payment_method_type.py
yookassa/domain/common/receipt_type.py
yookassa/domain/common/request_object.py
yookassa/domain/common/response_object.py
yookassa/domain/common/security_helper.py
yookassa/domain/common/type_factory.py
yookassa/domain/common/user_agent.py
yookassa/domain/exceptions/__init__.py
yookassa/domain/exceptions/api_error.py
yookassa/domain/exceptions/authorize_error.py
yookassa/domain/exceptions/bad_request_error.py
yookassa/domain/exceptions/forbidden_error.py
yookassa/domain/exceptions/not_found_error.py
yookassa/domain/exceptions/response_processing_error.py
yookassa/domain/exceptions/too_many_request_error.py
yookassa/domain/exceptions/unauthorized_error.py
yookassa/domain/models/__init__.py
yookassa/domain/models/airline.py
yookassa/domain/models/amount.py
yookassa/domain/models/authorization_details.py
yookassa/domain/models/cancellation_details.py
yookassa/domain/models/confirmation/__init__.py
yookassa/domain/models/confirmation/confirmation.py
yookassa/domain/models/confirmation/confirmation_class_map.py
yookassa/domain/models/confirmation/confirmation_factory.py
yookassa/domain/models/confirmation/request/__init__.py
yookassa/domain/models/confirmation/request/confirmation_embedded.py
yookassa/domain/models/confirmation/request/confirmation_external.py
yookassa/domain/models/confirmation/request/confirmation_mobile_application.py
yookassa/domain/models/confirmation/request/confirmation_qr.py
yookassa/domain/models/confirmation/request/confirmation_redirect.py
yookassa/domain/models/confirmation/request/confirmation_request.py
yookassa/domain/models/confirmation/response/__init__.py
yookassa_async-0.1.5.dist-info/LICENSE
yookassa_async-0.1.5.dist-info/METADATA
yookassa_async-0.1.5.dist-info/WHEEL
yookassa_async-0.1.5.dist-info/RECORD
