Metadata-Version: 2.1
Name: yookassa-async
Version: 0.1.5
Summary: Based on work of https://github.com/tonchik-tm and main yookassa package
Author: Илья Снимщиков
Author-email: igsnimschikov@edu.hse.ru
Requires-Python: >=3.9,<4.0
Classifier: Programming Language :: Python :: 3
Classifier: Programming Language :: Python :: 3.9
Classifier: Programming Language :: Python :: 3.10
Classifier: Programming Language :: Python :: 3.11
Requires-Dist: deprecated (>=1.2.13,<2.0.0)
Requires-Dist: distro (>=1.8.0,<2.0.0)
Requires-Dist: httpx (>=0.24.0,<0.25.0)
Requires-Dist: netaddr (>=0.8.0,<0.9.0)
Requires-Dist: requests (>=2.28.2,<3.0.0)
